learn_py_packaging/__init__.py
learn_py_packaging/math.py
learn_py_packaging/toy_module.py
learn_py_packaging_ae-0.1.0.dist-info/LICENSE
learn_py_packaging_ae-0.1.0.dist-info/METADATA
learn_py_packaging_ae-0.1.0.dist-info/WHEEL
learn_py_packaging_ae-0.1.0.dist-info/top_level.txt
learn_py_packaging_ae-0.1.0.dist-info/RECORD
