Metadata-Version: 2.1
Name: learn-py-packaging-ae
Version: 0.1.0
Summary: Demo python package
Home-page: https://github.com/aeverall/learn-py-packaging
Author: Andrew Everall
Author-email: andrew.everall1995@gmail.com
License: MIT
Platform: UNKNOWN
Requires-Python: >=3.7
License-File: LICENSE
Requires-Dist: numpy (>=1.9.0)
Requires-Dist: pandas
Provides-Extra: dev
Requires-Dist: bump2version ; extra == 'dev'
Requires-Dist: pytest ; extra == 'dev'
Requires-Dist: flake8 ; extra == 'dev'
Requires-Dist: black ; extra == 'dev'
Requires-Dist: mypy ; extra == 'dev'
